main.py
jira_confluence_mcp-0.5.9.dist-info/METADATA
jira_confluence_mcp-0.5.9.dist-info/WHEEL
jira_confluence_mcp-0.5.9.dist-info/entry_points.txt
jira_confluence_mcp-0.5.9.dist-info/top_level.txt
jira_confluence_mcp-0.5.9.dist-info/RECORD
