Metadata-Version: 2.4
Name: jira-confluence-mcp
Version: 0.5.9
Summary: jira-confluence-mcp is a Model Context Protocol (MCP) server that provides a standardized way for AI models to access and interact with resources from Jira and Confluence.
Project-URL: Repository, https://github.com/mooskim/jira-confluence-mcp.git
Requires-Python: >=3.12
Requires-Dist: mcp>=1.15.0
Requires-Dist: requests>=2.32.5
